nalibsAWSEKS/__base.py
nalibsAWSEKS/__init__.py
nalibsAWSEKS/__version.py
nalibsAWSEKS/aws_sm_func.py
nalibsAWSEKS/common.py
nalibsAWSEKS/eks_func.py
nalibsAWSEKS/tmpl.dotenv_config.j2
nalibsAWSEKS/x0_cli_cicd.py
nalibs_aws_eks-0.4.1.dist-info/LICENSE
nalibs_aws_eks-0.4.1.dist-info/METADATA
nalibs_aws_eks-0.4.1.dist-info/WHEEL
nalibs_aws_eks-0.4.1.dist-info/entry_points.txt
nalibs_aws_eks-0.4.1.dist-info/top_level.txt
nalibs_aws_eks-0.4.1.dist-info/RECORD
